[ {
  "artistName" : "Roddy Ricch",
  "segment" : "Previously Active Listeners"
}, {
  "artistName" : "Amrinder Gill",
  "segment" : "Light listeners"
}, {
  "artistName" : "Alemán",
  "segment" : "Previously Active Listeners"
}, {
  "artistName" : "DJ Spinz",
  "segment" : "Previously Active Listeners"
}, {
  "artistName" : "Taylor Swift",
  "segment" : "Previously Active Listeners"
}, {
  "artistName" : "Nedarb",
  "segment" : "Previously Active Listeners"
}, {
  "artistName" : "Sidewalks and Skeletons",
  "segment" : "Moderate listeners"
}, {
  "artistName" : "Yungstar",
  "segment" : "Previously Active Listeners"
}, {
  "artistName" : "Teddy Swims",
  "segment" : "Previously Active Listeners"
}, {
  "artistName" : "lil lagosta",
  "segment" : "Previously Active Listeners"
}, {
  "artistName" : "Ariana Grande",
  "segment" : "Previously Active Listeners"
}, {
  "artistName" : "XanGang",
  "segment" : "Previously Active Listeners"
}, {
  "artistName" : "Black Kray",
  "segment" : "Light listeners"
}, {
  "artistName" : "2hollis",
  "segment" : "Previously Active Listeners"
}, {
  "artistName" : "Lakeyah",
  "segment" : "Previously Active Listeners"
}, {
  "artistName" : "Yo Gotti",
  "segment" : "Light listeners"
}, {
  "artistName" : "CHASE B",
  "segment" : "Previously Active Listeners"
}, {
  "artistName" : "Stoney Rax",
  "segment" : "Light listeners"
}, {
  "artistName" : "lique",
  "segment" : "Previously Active Listeners"
}, {
  "artistName" : "Bee Gees",
  "segment" : "Light listeners"
}, {
  "artistName" : "Glokk40Spaz",
  "segment" : "Light listeners"
}, {
  "artistName" : "Oh Wonder",
  "segment" : "Previously Active Listeners"
}, {
  "artistName" : "Hotboii",
  "segment" : "Previously Active Listeners"
}, {
  "artistName" : "Cyndi Lauper",
  "segment" : "Previously Active Listeners"
}, {
  "artistName" : "VonOff1700",
  "segment" : "Previously Active Listeners"
}, {
  "artistName" : "XXXTENTACION",
  "segment" : "Previously Active Listeners"
}, {
  "artistName" : "buoa",
  "segment" : "Previously Active Listeners"
}, {
  "artistName" : "G Herbo",
  "segment" : "Previously Active Listeners"
}, {
  "artistName" : "HH",
  "segment" : "Super Listeners"
}, {
  "artistName" : "Duwap Kaine",
  "segment" : "Moderate listeners"
}, {
  "artistName" : "Lil Wayne",
  "segment" : "Previously Active Listeners"
}, {
  "artistName" : "BONES",
  "segment" : "Moderate listeners"
}, {
  "artistName" : "Rollin Thrax",
  "segment" : "Moderate listeners"
}, {
  "artistName" : "a$ap",
  "segment" : "Previously Active Listeners"
}, {
  "artistName" : "Glen Campbell",
  "segment" : "Light listeners"
}, {
  "artistName" : "FCG Heem",
  "segment" : "Light listeners"
}, {
  "artistName" : "Lil Tjay",
  "segment" : "Previously Active Listeners"
}, {
  "artistName" : "Fateh",
  "segment" : "Light listeners"
}, {
  "artistName" : "Chani Nattan",
  "segment" : "Previously Active Listeners"
}, {
  "artistName" : "Woodboy Gee",
  "segment" : "Light listeners"
}, {
  "artistName" : "wav",
  "segment" : "Previously Active Listeners"
}, {
  "artistName" : "Pollari",
  "segment" : "Previously Active Listeners"
}, {
  "artistName" : "YG",
  "segment" : "Previously Active Listeners"
}, {
  "artistName" : "rokkout",
  "segment" : "Previously Active Listeners"
}, {
  "artistName" : "AR Paisley",
  "segment" : "Previously Active Listeners"
}, {
  "artistName" : "YFN Lucci",
  "segment" : "Previously Active Listeners"
}, {
  "artistName" : "Sandesh Shandilya",
  "segment" : "Light listeners"
}, {
  "artistName" : "The Cars",
  "segment" : "Light listeners"
}, {
  "artistName" : "KR$NA",
  "segment" : "Previously Active Listeners"
}, {
  "artistName" : "Tefflon",
  "segment" : "Light listeners"
}, {
  "artistName" : "Tommy Richman",
  "segment" : "Previously Active Listeners"
}, {
  "artistName" : "Fetty Wap",
  "segment" : "Super Listeners"
}, {
  "artistName" : "Daaku",
  "segment" : "Previously Active Listeners"
}, {
  "artistName" : "The Stone Roses",
  "segment" : "Light listeners"
}, {
  "artistName" : "user00xman",
  "segment" : "Previously Active Listeners"
}, {
  "artistName" : "Gala",
  "segment" : "Previously Active Listeners"
}, {
  "artistName" : "Pat Ron",
  "segment" : "Previously Active Listeners"
}, {
  "artistName" : "SSGKobe",
  "segment" : "Previously Active Listeners"
}, {
  "artistName" : "Himesh Reshammiya",
  "segment" : "Previously Active Listeners"
}, {
  "artistName" : "Cigarettes After Sex",
  "segment" : "Light listeners"
}, {
  "artistName" : "Rashid Khan",
  "segment" : "Light listeners"
}, {
  "artistName" : "Robin Schulz",
  "segment" : "Light listeners"
}, {
  "artistName" : "Bffbenn",
  "segment" : "Moderate listeners"
}, {
  "artistName" : "Lil Poppa",
  "segment" : "Moderate listeners"
}, {
  "artistName" : "Tiakola",
  "segment" : "Previously Active Listeners"
}, {
  "artistName" : "Swapa",
  "segment" : "Previously Active Listeners"
}, {
  "artistName" : "Abhijay Sharma",
  "segment" : "Previously Active Listeners"
}, {
  "artistName" : "wonder",
  "segment" : "Previously Active Listeners"
}, {
  "artistName" : "Harold Budd",
  "segment" : "Previously Active Listeners"
}, {
  "artistName" : "Cold Hart",
  "segment" : "Previously Active Listeners"
}, {
  "artistName" : "Irshad Kamil",
  "segment" : "Light listeners"
}, {
  "artistName" : "B6",
  "segment" : "Previously Active Listeners"
}, {
  "artistName" : "TV Girl",
  "segment" : "Light listeners"
}, {
  "artistName" : "Karan Aujla",
  "segment" : "Previously Active Listeners"
}, {
  "artistName" : "purzs",
  "segment" : "Previously Active Listeners"
}, {
  "artistName" : "Grailed!",
  "segment" : "Previously Active Listeners"
}, {
  "artistName" : "PBN",
  "segment" : "Light listeners"
}, {
  "artistName" : "LENATERRA",
  "segment" : "Previously Active Listeners"
}, {
  "artistName" : "Birdman",
  "segment" : "Moderate listeners"
}, {
  "artistName" : "THE ANXIETY",
  "segment" : "Previously Active Listeners"
}, {
  "artistName" : "nett covers",
  "segment" : "Previously Active Listeners"
}, {
  "artistName" : "Migos",
  "segment" : "Previously Active Listeners"
}, {
  "artistName" : "Shoreline Mafia",
  "segment" : "Previously Active Listeners"
}, {
  "artistName" : "Hoobastank",
  "segment" : "Previously Active Listeners"
}, {
  "artistName" : "HardRock",
  "segment" : "Previously Active Listeners"
}, {
  "artistName" : "Cults",
  "segment" : "Previously Active Listeners"
}, {
  "artistName" : "The Chainsmokers",
  "segment" : "Previously Active Listeners"
}, {
  "artistName" : "absolute",
  "segment" : "Previously Active Listeners"
}, {
  "artistName" : "Tommy Newport",
  "segment" : "Previously Active Listeners"
}, {
  "artistName" : "Yung Kayo",
  "segment" : "Light listeners"
}, {
  "artistName" : "2Scratch",
  "segment" : "Light listeners"
}, {
  "artistName" : "Trey Bands",
  "segment" : "Previously Active Listeners"
}, {
  "artistName" : "Nicki Minaj",
  "segment" : "Previously Active Listeners"
}, {
  "artistName" : "Holy Mob",
  "segment" : "Light listeners"
}, {
  "artistName" : "Kanye West",
  "segment" : "Previously Active Listeners"
}, {
  "artistName" : "bulletproof",
  "segment" : "Previously Active Listeners"
}, {
  "artistName" : "junesforever",
  "segment" : "Previously Active Listeners"
}, {
  "artistName" : "ThereGoMarcus",
  "segment" : "Previously Active Listeners"
}, {
  "artistName" : "Nettspend",
  "segment" : "Moderate listeners"
}, {
  "artistName" : "Kvng Rome",
  "segment" : "Previously Active Listeners"
}, {
  "artistName" : "Coi Leray",
  "segment" : "Previously Active Listeners"
}, {
  "artistName" : "Lil Double 0",
  "segment" : "Super Listeners"
}, {
  "artistName" : "kodylayt",
  "segment" : "Previously Active Listeners"
}, {
  "artistName" : "BBG Baby Joe",
  "segment" : "Previously Active Listeners"
}, {
  "artistName" : "smokedope2016",
  "segment" : "Previously Active Listeners"
}, {
  "artistName" : "Fimiguerrero",
  "segment" : "Previously Active Listeners"
}, {
  "artistName" : "George Jason",
  "segment" : "Previously Active Listeners"
}, {
  "artistName" : "Jorjiana",
  "segment" : "Previously Active Listeners"
}, {
  "artistName" : "23 On Him",
  "segment" : "Previously Active Listeners"
}, {
  "artistName" : "Bob Marley & The Wailers",
  "segment" : "Previously Active Listeners"
}, {
  "artistName" : "Raj Bains",
  "segment" : "Light listeners"
}, {
  "artistName" : "Lana Del Rey",
  "segment" : "Previously Active Listeners"
}, {
  "artistName" : "Various Artists",
  "segment" : "Previously Active Listeners"
}, {
  "artistName" : "WILLOW",
  "segment" : "Moderate listeners"
}, {
  "artistName" : "Offset",
  "segment" : "Previously Active Listeners"
}, {
  "artistName" : "A.R. Rahman",
  "segment" : "Previously Active Listeners"
}, {
  "artistName" : "Crazy Frog",
  "segment" : "Previously Active Listeners"
}, {
  "artistName" : "KirbLaGoop",
  "segment" : "Previously Active Listeners"
}, {
  "artistName" : "Fluhkunxhkos",
  "segment" : "Previously Active Listeners"
}, {
  "artistName" : "gorn",
  "segment" : "Previously Active Listeners"
}, {
  "artistName" : "Key Glock",
  "segment" : "Previously Active Listeners"
}, {
  "artistName" : "Len",
  "segment" : "Previously Active Listeners"
}, {
  "artistName" : "11-1 Music",
  "segment" : "Previously Active Listeners"
}, {
  "artistName" : "fakemink",
  "segment" : "Previously Active Listeners"
}, {
  "artistName" : "Nick Jonas",
  "segment" : "Previously Active Listeners"
}, {
  "artistName" : "Hydranin",
  "segment" : "Previously Active Listeners"
}, {
  "artistName" : "drippxyblue",
  "segment" : "Previously Active Listeners"
}, {
  "artistName" : "Justin Bieber",
  "segment" : "Previously Active Listeners"
}, {
  "artistName" : "Ifys",
  "segment" : "Previously Active Listeners"
}, {
  "artistName" : "BunnaB",
  "segment" : "Previously Active Listeners"
}, {
  "artistName" : "Jeremih",
  "segment" : "Previously Active Listeners"
}, {
  "artistName" : "Danger Incorporated",
  "segment" : "Previously Active Listeners"
}, {
  "artistName" : "Young Dolph",
  "segment" : "Super Listeners"
}, {
  "artistName" : "Never Broke Again",
  "segment" : "Light listeners"
}, {
  "artistName" : "freazyy",
  "segment" : "Previously Active Listeners"
}, {
  "artistName" : "Whirr",
  "segment" : "Previously Active Listeners"
}, {
  "artistName" : "Speed Gang",
  "segment" : "Previously Active Listeners"
}, {
  "artistName" : "Umair",
  "segment" : "Previously Active Listeners"
}, {
  "artistName" : "FattMack",
  "segment" : "Previously Active Listeners"
}, {
  "artistName" : "James Blake",
  "segment" : "Previously Active Listeners"
}, {
  "artistName" : "Salim–Sulaiman",
  "segment" : "Previously Active Listeners"
}, {
  "artistName" : "Future",
  "segment" : "Super Listeners"
}, {
  "artistName" : "Starboy X",
  "segment" : "Previously Active Listeners"
}, {
  "artistName" : "Alka Yagnik",
  "segment" : "Previously Active Listeners"
}, {
  "artistName" : "Phil Jay",
  "segment" : "Previously Active Listeners"
}, {
  "artistName" : "ApolloRed1",
  "segment" : "Previously Active Listeners"
}, {
  "artistName" : "MDMA",
  "segment" : "Previously Active Listeners"
}, {
  "artistName" : "YNW Melly",
  "segment" : "Previously Active Listeners"
}, {
  "artistName" : "RGP Royal",
  "segment" : "Previously Active Listeners"
}, {
  "artistName" : "Javed Ali",
  "segment" : "Previously Active Listeners"
}, {
  "artistName" : "Frank Ocean",
  "segment" : "Previously Active Listeners"
}, {
  "artistName" : "Prem & Hardeep",
  "segment" : "Previously Active Listeners"
}, {
  "artistName" : "A$AP Rocky",
  "segment" : "Previously Active Listeners"
}, {
  "artistName" : "Finesse2tymes",
  "segment" : "Previously Active Listeners"
}, {
  "artistName" : "Byg Byrd",
  "segment" : "Previously Active Listeners"
}, {
  "artistName" : "steg0ri",
  "segment" : "Previously Active Listeners"
}, {
  "artistName" : "Lil Jon & The East Side Boyz",
  "segment" : "Previously Active Listeners"
}, {
  "artistName" : "Yunosa",
  "segment" : "Light listeners"
}, {
  "artistName" : "Juice WRLD",
  "segment" : "Previously Active Listeners"
}, {
  "artistName" : "Gente De Zona",
  "segment" : "Previously Active Listeners"
}, {
  "artistName" : "RYXH!",
  "segment" : "Previously Active Listeners"
}, {
  "artistName" : "Various Artists",
  "segment" : "Previously Active Listeners"
}, {
  "artistName" : "Eric Bellinger",
  "segment" : "Previously Active Listeners"
}, {
  "artistName" : "Ne-Yo",
  "segment" : "Previously Active Listeners"
}, {
  "artistName" : "Rob Vicious",
  "segment" : "Previously Active Listeners"
}, {
  "artistName" : "Vacosay",
  "segment" : "Previously Active Listeners"
}, {
  "artistName" : "Selena Gomez",
  "segment" : "Previously Active Listeners"
}, {
  "artistName" : "DaMil",
  "segment" : "Previously Active Listeners"
}, {
  "artistName" : "Selena Gomez & The Scene",
  "segment" : "Previously Active Listeners"
}, {
  "artistName" : "jahhde",
  "segment" : "Previously Active Listeners"
}, {
  "artistName" : "Cocteau Twins",
  "segment" : "Light listeners"
}, {
  "artistName" : "Purple Posse",
  "segment" : "Light listeners"
}, {
  "artistName" : "Real Boston Richey",
  "segment" : "Previously Active Listeners"
}, {
  "artistName" : "Sk8star",
  "segment" : "Previously Active Listeners"
}, {
  "artistName" : "YKNIECE",
  "segment" : "Previously Active Listeners"
}, {
  "artistName" : "Lil Tracy",
  "segment" : "Super Listeners"
}, {
  "artistName" : "RXLVND",
  "segment" : "Moderate listeners"
}, {
  "artistName" : "NoCap",
  "segment" : "Moderate listeners"
}, {
  "artistName" : "Montana 700",
  "segment" : "Light listeners"
}, {
  "artistName" : "Playboi Carti",
  "segment" : "Previously Active Listeners"
}, {
  "artistName" : "Tulsi Kumar",
  "segment" : "Light listeners"
}, {
  "artistName" : "Jus Reign",
  "segment" : "Previously Active Listeners"
}, {
  "artistName" : "Hector Vae",
  "segment" : "Previously Active Listeners"
}, {
  "artistName" : "Zaytoven",
  "segment" : "Previously Active Listeners"
}, {
  "artistName" : "Money Man",
  "segment" : "Moderate listeners"
}, {
  "artistName" : "Miinky",
  "segment" : "Previously Active Listeners"
}, {
  "artistName" : "Enchanting",
  "segment" : "Previously Active Listeners"
}, {
  "artistName" : "Prodgk",
  "segment" : "Previously Active Listeners"
}, {
  "artistName" : "Ratna",
  "segment" : "Previously Active Listeners"
}, {
  "artistName" : "Afsana Khan",
  "segment" : "Previously Active Listeners"
}, {
  "artistName" : "Dhanju",
  "segment" : "Light listeners"
}, {
  "artistName" : "Sia",
  "segment" : "Previously Active Listeners"
}, {
  "artistName" : "Viktor Vaughn",
  "segment" : "Previously Active Listeners"
}, {
  "artistName" : "xaviersobased",
  "segment" : "Previously Active Listeners"
}, {
  "artistName" : "Beyoncé",
  "segment" : "Previously Active Listeners"
}, {
  "artistName" : "PLUTO",
  "segment" : "Previously Active Listeners"
}, {
  "artistName" : "Amitabh Bhattacharya",
  "segment" : "Previously Active Listeners"
}, {
  "artistName" : "Prettyheartbreak",
  "segment" : "Previously Active Listeners"
}, {
  "artistName" : "Molella",
  "segment" : "Previously Active Listeners"
}, {
  "artistName" : "Destroy Lonely",
  "segment" : "Moderate listeners"
}, {
  "artistName" : "Jaz Dhami",
  "segment" : "Previously Active Listeners"
}, {
  "artistName" : "SSENMELO",
  "segment" : "Previously Active Listeners"
}, {
  "artistName" : "Mazzy Star",
  "segment" : "Light listeners"
}, {
  "artistName" : "bruh young",
  "segment" : "Previously Active Listeners"
}, {
  "artistName" : "Smrtdeath",
  "segment" : "Previously Active Listeners"
}, {
  "artistName" : "Germ",
  "segment" : "Previously Active Listeners"
}, {
  "artistName" : "Audereus",
  "segment" : "Previously Active Listeners"
}, {
  "artistName" : "Mint Condition",
  "segment" : "Previously Active Listeners"
}, {
  "artistName" : "John Newman",
  "segment" : "Previously Active Listeners"
}, {
  "artistName" : "Tems",
  "segment" : "Previously Active Listeners"
}, {
  "artistName" : "Francesco Yates",
  "segment" : "Light listeners"
}, {
  "artistName" : "Rod Wave",
  "segment" : "Light listeners"
}, {
  "artistName" : "Grimes",
  "segment" : "Moderate listeners"
}, {
  "artistName" : "Imran Khan",
  "segment" : "Light listeners"
}, {
  "artistName" : "Reptilian Club Boyz",
  "segment" : "Previously Active Listeners"
}, {
  "artistName" : "Young Scooter",
  "segment" : "Previously Active Listeners"
}, {
  "artistName" : "Cxupsean",
  "segment" : "Previously Active Listeners"
}, {
  "artistName" : "Yung Bans",
  "segment" : "Previously Active Listeners"
}, {
  "artistName" : "Sosamann",
  "segment" : "Previously Active Listeners"
}, {
  "artistName" : "Quality Control",
  "segment" : "Previously Active Listeners"
}, {
  "artistName" : "Beach Fossils",
  "segment" : "Previously Active Listeners"
}, {
  "artistName" : "Taurusi",
  "segment" : "Light listeners"
}, {
  "artistName" : "Aaron May",
  "segment" : "Previously Active Listeners"
}, {
  "artistName" : "Diorvsyou",
  "segment" : "Moderate listeners"
}, {
  "artistName" : "Sleepy Hallow",
  "segment" : "Previously Active Listeners"
}, {
  "artistName" : "lagosta",
  "segment" : "Previously Active Listeners"
}, {
  "artistName" : "Yeat Leaked",
  "segment" : "Previously Active Listeners"
}, {
  "artistName" : "majorforever",
  "segment" : "Previously Active Listeners"
}, {
  "artistName" : "Zillionaire Doe",
  "segment" : "Super Listeners"
}, {
  "artistName" : "osamaarchivo",
  "segment" : "Previously Active Listeners"
}, {
  "artistName" : "Armut",
  "segment" : "Previously Active Listeners"
}, {
  "artistName" : "Neton Vega",
  "segment" : "Previously Active Listeners"
}, {
  "artistName" : "Vishal-Shekhar",
  "segment" : "Previously Active Listeners"
}, {
  "artistName" : "Bladee",
  "segment" : "Light listeners"
}, {
  "artistName" : "FortyKnivez",
  "segment" : "Previously Active Listeners"
}, {
  "artistName" : "Lil Uzi Vert",
  "segment" : "Previously Active Listeners"
}, {
  "artistName" : "City Girls",
  "segment" : "Previously Active Listeners"
}, {
  "artistName" : "lilster",
  "segment" : "Previously Active Listeners"
}, {
  "artistName" : "Ikky",
  "segment" : "Previously Active Listeners"
}, {
  "artistName" : "Taliban Glizzy",
  "segment" : "Light listeners"
}, {
  "artistName" : "Percaso",
  "segment" : "Light listeners"
}, {
  "artistName" : "Swisha T",
  "segment" : "Light listeners"
}, {
  "artistName" : "Sickboyrari",
  "segment" : "Light listeners"
}, {
  "artistName" : "mist",
  "segment" : "Previously Active Listeners"
}, {
  "artistName" : "thiarajxtt",
  "segment" : "Light listeners"
}, {
  "artistName" : "Drippin So Pretty",
  "segment" : "Light listeners"
}, {
  "artistName" : "Vestron Vulture",
  "segment" : "Previously Active Listeners"
}, {
  "artistName" : "Russ",
  "segment" : "Previously Active Listeners"
}, {
  "artistName" : "Jassa Dhillon",
  "segment" : "Previously Active Listeners"
}, {
  "artistName" : "Lil Durk",
  "segment" : "Previously Active Listeners"
}, {
  "artistName" : "Arijit Singh",
  "segment" : "Light listeners"
}, {
  "artistName" : "The Smashing Pumpkins",
  "segment" : "Light listeners"
}, {
  "artistName" : "Fatboibari",
  "segment" : "Light listeners"
}, {
  "artistName" : "The Cranberries",
  "segment" : "Previously Active Listeners"
}, {
  "artistName" : "SoFaygo",
  "segment" : "Light listeners"
}, {
  "artistName" : "Mayur Puri",
  "segment" : "Previously Active Listeners"
}, {
  "artistName" : "Moneybagg Yo",
  "segment" : "Light listeners"
}, {
  "artistName" : "Iluvhuncho",
  "segment" : "Previously Active Listeners"
}, {
  "artistName" : "Yoko Gold",
  "segment" : "Previously Active Listeners"
}, {
  "artistName" : "Alisha Chinai",
  "segment" : "Previously Active Listeners"
}, {
  "artistName" : "wtfadamik",
  "segment" : "Previously Active Listeners"
}, {
  "artistName" : "Travis Scott",
  "segment" : "Previously Active Listeners"
}, {
  "artistName" : "SB",
  "segment" : "Previously Active Listeners"
}, {
  "artistName" : "wonder archive",
  "segment" : "Previously Active Listeners"
}, {
  "artistName" : "Meek Mill",
  "segment" : "Previously Active Listeners"
}, {
  "artistName" : "YoungBoy Never Broke Again",
  "segment" : "Super Listeners"
}, {
  "artistName" : "Geeka Kid",
  "segment" : "Previously Active Listeners"
}, {
  "artistName" : "Greg Kurstin",
  "segment" : "Previously Active Listeners"
}, {
  "artistName" : "Men I Trust",
  "segment" : "Light listeners"
}, {
  "artistName" : "Tame Impala",
  "segment" : "Previously Active Listeners"
}, {
  "artistName" : "ksuuvi",
  "segment" : "Previously Active Listeners"
}, {
  "artistName" : "The Police",
  "segment" : "Previously Active Listeners"
}, {
  "artistName" : "6LACK",
  "segment" : "Previously Active Listeners"
}, {
  "artistName" : "Yung Bruh",
  "segment" : "Super Listeners"
}, {
  "artistName" : "lagostaah",
  "segment" : "Previously Active Listeners"
}, {
  "artistName" : "Lil Rae",
  "segment" : "Previously Active Listeners"
}, {
  "artistName" : "Jay Trak",
  "segment" : "Light listeners"
}, {
  "artistName" : "Eyedress",
  "segment" : "Previously Active Listeners"
}, {
  "artistName" : "Shreya Ghoshal",
  "segment" : "Previously Active Listeners"
}, {
  "artistName" : "Brennan Jones",
  "segment" : "Moderate listeners"
}, {
  "artistName" : "Devilish Trio",
  "segment" : "Light listeners"
}, {
  "artistName" : "Kanika Kapoor",
  "segment" : "Previously Active Listeners"
}, {
  "artistName" : "88GLAM",
  "segment" : "Light listeners"
}, {
  "artistName" : "vampcult",
  "segment" : "Super Listeners"
}, {
  "artistName" : "killmykel",
  "segment" : "Moderate listeners"
}, {
  "artistName" : "Hikaru Utada",
  "segment" : "Previously Active Listeners"
}, {
  "artistName" : "A$AP Ferg",
  "segment" : "Light listeners"
}, {
  "artistName" : "Avvy Sra",
  "segment" : "Previously Active Listeners"
}, {
  "artistName" : "Hunxho",
  "segment" : "Previously Active Listeners"
}, {
  "artistName" : "Grind2hard Osh’a",
  "segment" : "Light listeners"
}, {
  "artistName" : "King George",
  "segment" : "Previously Active Listeners"
}, {
  "artistName" : "Curren$y",
  "segment" : "Previously Active Listeners"
}, {
  "artistName" : ".cutspace",
  "segment" : "Previously Active Listeners"
}, {
  "artistName" : "Dream, Ivory",
  "segment" : "Previously Active Listeners"
}, {
  "artistName" : "Descemer Bueno",
  "segment" : "Previously Active Listeners"
}, {
  "artistName" : "osa u,_u",
  "segment" : "Previously Active Listeners"
}, {
  "artistName" : "Yyreatboy",
  "segment" : "Previously Active Listeners"
}, {
  "artistName" : "Crowded House",
  "segment" : "Previously Active Listeners"
}, {
  "artistName" : "Yung Bleu",
  "segment" : "Light listeners"
}, {
  "artistName" : "Mickey Singh",
  "segment" : "Previously Active Listeners"
}, {
  "artistName" : "Glass Candy",
  "segment" : "Previously Active Listeners"
}, {
  "artistName" : "Maybank",
  "segment" : "Previously Active Listeners"
}, {
  "artistName" : "D. Savage",
  "segment" : "Previously Active Listeners"
}, {
  "artistName" : "blazed",
  "segment" : "Previously Active Listeners"
}, {
  "artistName" : "Swae Lee",
  "segment" : "Previously Active Listeners"
}, {
  "artistName" : "Rylo Rodriguez",
  "segment" : "Previously Active Listeners"
}, {
  "artistName" : "Skooly",
  "segment" : "Previously Active Listeners"
}, {
  "artistName" : "LSD and the Search for God",
  "segment" : "Previously Active Listeners"
}, {
  "artistName" : "Don Toliver",
  "segment" : "Super Listeners"
}, {
  "artistName" : "Tove Lo",
  "segment" : "Previously Active Listeners"
}, {
  "artistName" : "Sowhatimdead",
  "segment" : "Moderate listeners"
}, {
  "artistName" : "YK Niece",
  "segment" : "Previously Active Listeners"
}, {
  "artistName" : "The Smiths",
  "segment" : "Previously Active Listeners"
}, {
  "artistName" : "Sukha",
  "segment" : "Light listeners"
}, {
  "artistName" : "Chase Shakur",
  "segment" : "Previously Active Listeners"
}, {
  "artistName" : "sixteen",
  "segment" : "Previously Active Listeners"
}, {
  "artistName" : "Acid Ghost",
  "segment" : "Previously Active Listeners"
}, {
  "artistName" : "doomedwtf",
  "segment" : "Previously Active Listeners"
}, {
  "artistName" : "Xavier Wulf",
  "segment" : "Moderate listeners"
}, {
  "artistName" : "Rico Dinero",
  "segment" : "Previously Active Listeners"
}, {
  "artistName" : "Ty Dolla $ign",
  "segment" : "Previously Active Listeners"
}, {
  "artistName" : "Ken Carson",
  "segment" : "Light listeners"
}, {
  "artistName" : "tasah",
  "segment" : "Previously Active Listeners"
}, {
  "artistName" : "Loe Shimmy",
  "segment" : "Super Listeners"
}, {
  "artistName" : "scarycide",
  "segment" : "Previously Active Listeners"
}, {
  "artistName" : "SahBabii",
  "segment" : "Light listeners"
}, {
  "artistName" : "EsDeeKid",
  "segment" : "Previously Active Listeners"
}, {
  "artistName" : "Devstacks",
  "segment" : "Previously Active Listeners"
}, {
  "artistName" : "Quiixy",
  "segment" : "Previously Active Listeners"
}, {
  "artistName" : "Phee6z",
  "segment" : "Previously Active Listeners"
}, {
  "artistName" : "Anti Da Menace",
  "segment" : "Previously Active Listeners"
}, {
  "artistName" : "Victoria Monét",
  "segment" : "Previously Active Listeners"
}, {
  "artistName" : "Sunidhi Chauhan",
  "segment" : "Previously Active Listeners"
}, {
  "artistName" : "rich disease",
  "segment" : "Previously Active Listeners"
}, {
  "artistName" : "Master Kato",
  "segment" : "Previously Active Listeners"
}, {
  "artistName" : "GothBoiClique",
  "segment" : "Light listeners"
}, {
  "artistName" : "Sielanna",
  "segment" : "Previously Active Listeners"
}, {
  "artistName" : "Fredo Bang",
  "segment" : "Previously Active Listeners"
}, {
  "artistName" : "Talwiinder",
  "segment" : "Previously Active Listeners"
}, {
  "artistName" : "The Marías",
  "segment" : "Light listeners"
}, {
  "artistName" : "Big Boogie",
  "segment" : "Previously Active Listeners"
}, {
  "artistName" : "Roop Kumar Rathod",
  "segment" : "Previously Active Listeners"
}, {
  "artistName" : "Billy Joel",
  "segment" : "Previously Active Listeners"
}, {
  "artistName" : "2wo2imes",
  "segment" : "Previously Active Listeners"
}, {
  "artistName" : "neverlose",
  "segment" : "Previously Active Listeners"
}, {
  "artistName" : "Autumn's Grey Solace",
  "segment" : "Previously Active Listeners"
}, {
  "artistName" : "xtcsyyy",
  "segment" : "Previously Active Listeners"
}, {
  "artistName" : "maxon",
  "segment" : "Previously Active Listeners"
}, {
  "artistName" : "44spellz",
  "segment" : "Previously Active Listeners"
}, {
  "artistName" : "5eva",
  "segment" : "Super Listeners"
}, {
  "artistName" : "Dj Smokey",
  "segment" : "Previously Active Listeners"
}, {
  "artistName" : "The Neighbourhood",
  "segment" : "Light listeners"
}, {
  "artistName" : "Yvngxadonis",
  "segment" : "Previously Active Listeners"
}, {
  "artistName" : "Baby Smoove",
  "segment" : "Moderate listeners"
}, {
  "artistName" : "Yungeen Ace",
  "segment" : "Previously Active Listeners"
}, {
  "artistName" : "Zickplant",
  "segment" : "Previously Active Listeners"
}, {
  "artistName" : "BabyChiefDoit",
  "segment" : "Previously Active Listeners"
}, {
  "artistName" : "APPLERK",
  "segment" : "Previously Active Listeners"
}, {
  "artistName" : "Foolio",
  "segment" : "Previously Active Listeners"
}, {
  "artistName" : "Rich Amiri",
  "segment" : "Previously Active Listeners"
}, {
  "artistName" : "GIVĒON",
  "segment" : "Previously Active Listeners"
}, {
  "artistName" : "Mareux",
  "segment" : "Light listeners"
}, {
  "artistName" : "Shaan",
  "segment" : "Previously Active Listeners"
}, {
  "artistName" : "Sachin-Jigar",
  "segment" : "Previously Active Listeners"
}, {
  "artistName" : "VenesiaWorld",
  "segment" : "Previously Active Listeners"
}, {
  "artistName" : "fish narc",
  "segment" : "Moderate listeners"
}, {
  "artistName" : "Twinuzis archive",
  "segment" : "Previously Active Listeners"
}, {
  "artistName" : "salvia palth",
  "segment" : "Previously Active Listeners"
}, {
  "artistName" : "Tierra Whack",
  "segment" : "Previously Active Listeners"
}, {
  "artistName" : "Dean Blunt",
  "segment" : "Previously Active Listeners"
}, {
  "artistName" : "Sheck Wes",
  "segment" : "Previously Active Listeners"
}, {
  "artistName" : "Lil Jairmy",
  "segment" : "Previously Active Listeners"
}, {
  "artistName" : "Summer Walker",
  "segment" : "Previously Active Listeners"
}, {
  "artistName" : "Zaystarr",
  "segment" : "Previously Active Listeners"
}, {
  "artistName" : "NxxxxxS",
  "segment" : "Previously Active Listeners"
}, {
  "artistName" : "Avenoir",
  "segment" : "Previously Active Listeners"
}, {
  "artistName" : "babekhris",
  "segment" : "Previously Active Listeners"
}, {
  "artistName" : "Shrimp",
  "segment" : "Previously Active Listeners"
}, {
  "artistName" : "Xjay",
  "segment" : "Previously Active Listeners"
}, {
  "artistName" : "Kenzima",
  "segment" : "Previously Active Listeners"
}, {
  "artistName" : "21 Savage",
  "segment" : "Previously Active Listeners"
}, {
  "artistName" : "Johnny Mizenko",
  "segment" : "Previously Active Listeners"
}, {
  "artistName" : "Spalexma",
  "segment" : "Light listeners"
}, {
  "artistName" : "Palisades",
  "segment" : "Previously Active Listeners"
}, {
  "artistName" : "Mohit Chauhan",
  "segment" : "Light listeners"
}, {
  "artistName" : "Ramirez",
  "segment" : "Light listeners"
}, {
  "artistName" : "Mohammed Rafi",
  "segment" : "Previously Active Listeners"
}, {
  "artistName" : "sixsick",
  "segment" : "Previously Active Listeners"
}, {
  "artistName" : "Pouya",
  "segment" : "Previously Active Listeners"
}, {
  "artistName" : "youth",
  "segment" : "Previously Active Listeners"
}, {
  "artistName" : "luvrello",
  "segment" : "Previously Active Listeners"
}, {
  "artistName" : "Yot Club",
  "segment" : "Previously Active Listeners"
}, {
  "artistName" : "Asaku Fox",
  "segment" : "Previously Active Listeners"
}, {
  "artistName" : "Donna Lewis",
  "segment" : "Light listeners"
}, {
  "artistName" : "Memo Boy",
  "segment" : "Previously Active Listeners"
}, {
  "artistName" : "The Voidz",
  "segment" : "Previously Active Listeners"
}, {
  "artistName" : "Lil Baby",
  "segment" : "Moderate listeners"
}, {
  "artistName" : "Crystal Castles",
  "segment" : "Previously Active Listeners"
}, {
  "artistName" : "PinkPantheress",
  "segment" : "Previously Active Listeners"
}, {
  "artistName" : "days",
  "segment" : "Previously Active Listeners"
}, {
  "artistName" : "damezmp3",
  "segment" : "Previously Active Listeners"
}, {
  "artistName" : "Eminem",
  "segment" : "Previously Active Listeners"
}, {
  "artistName" : "KAYTRANADA",
  "segment" : "Previously Active Listeners"
}, {
  "artistName" : "Rooh Sandhu",
  "segment" : "Light listeners"
}, {
  "artistName" : "Big E",
  "segment" : "Previously Active Listeners"
}, {
  "artistName" : "XanGang",
  "segment" : "Previously Active Listeners"
}, {
  "artistName" : "Jawad Ahmad",
  "segment" : "Previously Active Listeners"
}, {
  "artistName" : "GloRilla",
  "segment" : "Previously Active Listeners"
}, {
  "artistName" : "BNYX®",
  "segment" : "Previously Active Listeners"
}, {
  "artistName" : "Rick Springfield",
  "segment" : "Previously Active Listeners"
}, {
  "artistName" : "a7chitec",
  "segment" : "Previously Active Listeners"
}, {
  "artistName" : "Craig Xen",
  "segment" : "Previously Active Listeners"
}, {
  "artistName" : "DarkFantasyInterlude",
  "segment" : "Previously Active Listeners"
}, {
  "artistName" : "Pastel Ghost",
  "segment" : "Light listeners"
}, {
  "artistName" : "qual",
  "segment" : "Previously Active Listeners"
}, {
  "artistName" : "sevensevenseven",
  "segment" : "Light listeners"
}, {
  "artistName" : "Tyrese",
  "segment" : "Previously Active Listeners"
}, {
  "artistName" : "Waka Flocka Flame",
  "segment" : "Previously Active Listeners"
}, {
  "artistName" : "$hyfromdatre",
  "segment" : "Previously Active Listeners"
}, {
  "artistName" : "SDMNR",
  "segment" : "Previously Active Listeners"
}, {
  "artistName" : "Hymbeats",
  "segment" : "Light listeners"
}, {
  "artistName" : "Mxrci",
  "segment" : "Previously Active Listeners"
}, {
  "artistName" : "freemyswag",
  "segment" : "Light listeners"
}, {
  "artistName" : "EKKSTACY",
  "segment" : "Previously Active Listeners"
}, {
  "artistName" : "sharkboy",
  "segment" : "Previously Active Listeners"
}, {
  "artistName" : "Faaiz Anwar",
  "segment" : "Light listeners"
}, {
  "artistName" : "Lucidity",
  "segment" : "Previously Active Listeners"
}, {
  "artistName" : "Paramore",
  "segment" : "Previously Active Listeners"
}, {
  "artistName" : "youngvampmoney",
  "segment" : "Previously Active Listeners"
}, {
  "artistName" : "x$ept",
  "segment" : "Previously Active Listeners"
}, {
  "artistName" : "Central Cee",
  "segment" : "Previously Active Listeners"
}, {
  "artistName" : "A Boogie Wit da Hoodie",
  "segment" : "Previously Active Listeners"
}, {
  "artistName" : "Blueface",
  "segment" : "Previously Active Listeners"
}, {
  "artistName" : "Lil Candy Paint",
  "segment" : "Moderate listeners"
}, {
  "artistName" : "Tyler Cole",
  "segment" : "Previously Active Listeners"
}, {
  "artistName" : "Jay Sean",
  "segment" : "Previously Active Listeners"
}, {
  "artistName" : "Miley Cyrus",
  "segment" : "Previously Active Listeners"
}, {
  "artistName" : "SosMula",
  "segment" : "Previously Active Listeners"
}, {
  "artistName" : "jtski",
  "segment" : "Previously Active Listeners"
}, {
  "artistName" : "Big Yavo",
  "segment" : "Previously Active Listeners"
}, {
  "artistName" : "Aloe Blacc",
  "segment" : "Light listeners"
}, {
  "artistName" : "blxcktai",
  "segment" : "Previously Active Listeners"
}, {
  "artistName" : "Clara La San",
  "segment" : "Light listeners"
}, {
  "artistName" : "BabyJake",
  "segment" : "Previously Active Listeners"
}, {
  "artistName" : "Soudiere",
  "segment" : "Previously Active Listeners"
}, {
  "artistName" : "foraw immunity shield",
  "segment" : "Previously Active Listeners"
}, {
  "artistName" : "Nelly Furtado",
  "segment" : "Previously Active Listeners"
}, {
  "artistName" : "dontevenworry",
  "segment" : "Previously Active Listeners"
}, {
  "artistName" : "shynemoonlight",
  "segment" : "Previously Active Listeners"
}, {
  "artistName" : "Lonerswrld!",
  "segment" : "Previously Active Listeners"
}, {
  "artistName" : "Tegi Pannu",
  "segment" : "Light listeners"
}, {
  "artistName" : "Shekhar Ravjiani",
  "segment" : "Previously Active Listeners"
}, {
  "artistName" : "Jaideep Sahni",
  "segment" : "Previously Active Listeners"
}, {
  "artistName" : "wound",
  "segment" : "Previously Active Listeners"
}, {
  "artistName" : "BANDY",
  "segment" : "Previously Active Listeners"
}, {
  "artistName" : "Mac DeMarco",
  "segment" : "Light listeners"
}, {
  "artistName" : "Sukihana",
  "segment" : "Previously Active Listeners"
}, {
  "artistName" : "Jamie Foxx",
  "segment" : "Previously Active Listeners"
}, {
  "artistName" : "Lil Peep",
  "segment" : "Moderate listeners"
}, {
  "artistName" : "Kishore Kumar",
  "segment" : "Previously Active Listeners"
}, {
  "artistName" : "Brent Faiyaz",
  "segment" : "Light listeners"
}, {
  "artistName" : "Nino Paid",
  "segment" : "Previously Active Listeners"
}, {
  "artistName" : "Nirmaan",
  "segment" : "Previously Active Listeners"
}, {
  "artistName" : "EST Gee",
  "segment" : "Previously Active Listeners"
}, {
  "artistName" : "Texako",
  "segment" : "Light listeners"
}, {
  "artistName" : "El Titø",
  "segment" : "Previously Active Listeners"
}, {
  "artistName" : "Metro Boomin",
  "segment" : "Light listeners"
}, {
  "artistName" : "Greg Kurstin",
  "segment" : "Previously Active Listeners"
}, {
  "artistName" : "lujoshfo",
  "segment" : "Previously Active Listeners"
}, {
  "artistName" : "EBK Jaaybo",
  "segment" : "Previously Active Listeners"
}, {
  "artistName" : "kdn",
  "segment" : "Previously Active Listeners"
}, {
  "artistName" : "Heembeezy",
  "segment" : "Previously Active Listeners"
}, {
  "artistName" : "kiru",
  "segment" : "Previously Active Listeners"
}, {
  "artistName" : "Highway",
  "segment" : "Moderate listeners"
}, {
  "artistName" : "Sona Mohapatra",
  "segment" : "Previously Active Listeners"
}, {
  "artistName" : "Chief Keef",
  "segment" : "Moderate listeners"
}, {
  "artistName" : "Quavo",
  "segment" : "Previously Active Listeners"
}, {
  "artistName" : "Night Lovell",
  "segment" : "Previously Active Listeners"
}, {
  "artistName" : "Enrique Iglesias",
  "segment" : "Previously Active Listeners"
}, {
  "artistName" : "Lancey Foux",
  "segment" : "Light listeners"
}, {
  "artistName" : "$uicideboy$",
  "segment" : "Light listeners"
}, {
  "artistName" : "goyardleopard",
  "segment" : "Super Listeners"
}, {
  "artistName" : "Yo Yo Honey Singh",
  "segment" : "Previously Active Listeners"
}, {
  "artistName" : "evicitionoflove",
  "segment" : "Previously Active Listeners"
}, {
  "artistName" : "FIYAH",
  "segment" : "Previously Active Listeners"
}, {
  "artistName" : "11:11",
  "segment" : "Previously Active Listeners"
}, {
  "artistName" : "lagosta<3",
  "segment" : "Previously Active Listeners"
}, {
  "artistName" : "stack$",
  "segment" : "Previously Active Listeners"
}, {
  "artistName" : "4batz",
  "segment" : "Previously Active Listeners"
}, {
  "artistName" : "Rico Ace",
  "segment" : "Previously Active Listeners"
}, {
  "artistName" : "Atl Smook",
  "segment" : "Moderate listeners"
}, {
  "artistName" : "Zaybeezy",
  "segment" : "Previously Active Listeners"
}, {
  "artistName" : "Phiec",
  "segment" : "Previously Active Listeners"
}, {
  "artistName" : "Ellie Goulding",
  "segment" : "Previously Active Listeners"
}, {
  "artistName" : "Ballout",
  "segment" : "Previously Active Listeners"
}, {
  "artistName" : "The Cure",
  "segment" : "Previously Active Listeners"
}, {
  "artistName" : "Slowdive",
  "segment" : "Moderate listeners"
}, {
  "artistName" : "Rot Ken",
  "segment" : "Previously Active Listeners"
}, {
  "artistName" : "Lucki Oxy",
  "segment" : "Previously Active Listeners"
}, {
  "artistName" : "BaroKar",
  "segment" : "Previously Active Listeners"
}, {
  "artistName" : "ssbeghost♱",
  "segment" : "Previously Active Listeners"
}, {
  "artistName" : "1600j",
  "segment" : "Light listeners"
}, {
  "artistName" : "NAV",
  "segment" : "Previously Active Listeners"
}, {
  "artistName" : "Sonder",
  "segment" : "Previously Active Listeners"
}, {
  "artistName" : "Speaker Knockerz",
  "segment" : "Previously Active Listeners"
}, {
  "artistName" : "iimHoodie",
  "segment" : "Previously Active Listeners"
}, {
  "artistName" : "Beach House",
  "segment" : "Light listeners"
}, {
  "artistName" : "Bir",
  "segment" : "Light listeners"
}, {
  "artistName" : "Chavo",
  "segment" : "Moderate listeners"
}, {
  "artistName" : "Nine Vicious",
  "segment" : "Moderate listeners"
}, {
  "artistName" : "Ayparia",
  "segment" : "Previously Active Listeners"
}, {
  "artistName" : "Summrs Vault",
  "segment" : "Previously Active Listeners"
}, {
  "artistName" : "mozopps",
  "segment" : "Previously Active Listeners"
}, {
  "artistName" : "blihss",
  "segment" : "Light listeners"
}, {
  "artistName" : "Nardo Wick",
  "segment" : "Previously Active Listeners"
}, {
  "artistName" : "zenn!",
  "segment" : "Previously Active Listeners"
}, {
  "artistName" : "Trippie Redd",
  "segment" : "Previously Active Listeners"
}, {
  "artistName" : "The Dream Academy",
  "segment" : "Light listeners"
}, {
  "artistName" : "gvcci kray",
  "segment" : "Previously Active Listeners"
}, {
  "artistName" : "Fourfive",
  "segment" : "Previously Active Listeners"
}, {
  "artistName" : "Lil Yachty",
  "segment" : "Light listeners"
}, {
  "artistName" : "Kodak Black",
  "segment" : "Previously Active Listeners"
}, {
  "artistName" : "Rihanna",
  "segment" : "Previously Active Listeners"
}, {
  "artistName" : "Mr.Kitty",
  "segment" : "Previously Active Listeners"
}, {
  "artistName" : "Badshah",
  "segment" : "Previously Active Listeners"
}, {
  "artistName" : "Jagjit Singh",
  "segment" : "Previously Active Listeners"
}, {
  "artistName" : "Lil Gnar",
  "segment" : "Previously Active Listeners"
}, {
  "artistName" : "Zaiteneh",
  "segment" : "Previously Active Listeners"
}, {
  "artistName" : "03 Greedo",
  "segment" : "Light listeners"
}, {
  "artistName" : "French Montana",
  "segment" : "Previously Active Listeners"
}, {
  "artistName" : "cirvekii",
  "segment" : "Previously Active Listeners"
}, {
  "artistName" : "Eem Triplin",
  "segment" : "Previously Active Listeners"
}, {
  "artistName" : "Savage Garden",
  "segment" : "Previously Active Listeners"
}, {
  "artistName" : "Sade",
  "segment" : "Previously Active Listeners"
}, {
  "artistName" : "PARTYNEXTDOOR",
  "segment" : "Light listeners"
}, {
  "artistName" : "Bedroom",
  "segment" : "Previously Active Listeners"
}, {
  "artistName" : "ICYTWAT",
  "segment" : "Previously Active Listeners"
}, {
  "artistName" : "Robb Bank$",
  "segment" : "Light listeners"
}, {
  "artistName" : "Ed Sheeran",
  "segment" : "Previously Active Listeners"
}, {
  "artistName" : "Babyface Ray",
  "segment" : "Moderate listeners"
}, {
  "artistName" : "GELO",
  "segment" : "Previously Active Listeners"
}, {
  "artistName" : "Trey Songz",
  "segment" : "Previously Active Listeners"
}, {
  "artistName" : "Pritam",
  "segment" : "Moderate listeners"
}, {
  "artistName" : "Starboy",
  "segment" : "Previously Active Listeners"
}, {
  "artistName" : "Mackned",
  "segment" : "Previously Active Listeners"
}, {
  "artistName" : "Crip Mac",
  "segment" : "Previously Active Listeners"
}, {
  "artistName" : "Protect",
  "segment" : "Moderate listeners"
}, {
  "artistName" : "Larry June",
  "segment" : "Light listeners"
}, {
  "artistName" : "Yung Joc",
  "segment" : "Previously Active Listeners"
}, {
  "artistName" : "Diern",
  "segment" : "Previously Active Listeners"
}, {
  "artistName" : "jssr",
  "segment" : "Light listeners"
}, {
  "artistName" : "9lokknine",
  "segment" : "Previously Active Listeners"
}, {
  "artistName" : "Pressa",
  "segment" : "Light listeners"
}, {
  "artistName" : "jinslime",
  "segment" : "Previously Active Listeners"
}, {
  "artistName" : "durk",
  "segment" : "Previously Active Listeners"
}, {
  "artistName" : "DJ ESCO",
  "segment" : "Previously Active Listeners"
}, {
  "artistName" : "B1benn",
  "segment" : "Previously Active Listeners"
}, {
  "artistName" : "Mikky Ekko",
  "segment" : "Previously Active Listeners"
}, {
  "artistName" : "prodbystarz",
  "segment" : "Previously Active Listeners"
}, {
  "artistName" : "Whethan",
  "segment" : "Previously Active Listeners"
}, {
  "artistName" : "Smokepurpp",
  "segment" : "Previously Active Listeners"
}, {
  "artistName" : "boygenius",
  "segment" : "Previously Active Listeners"
}, {
  "artistName" : "Yung Bruh",
  "segment" : "Previously Active Listeners"
}, {
  "artistName" : "DDG",
  "segment" : "Previously Active Listeners"
}, {
  "artistName" : "Ustad Sultan Khan",
  "segment" : "Previously Active Listeners"
}, {
  "artistName" : "Autumn!",
  "segment" : "Light listeners"
}, {
  "artistName" : "DaBaby",
  "segment" : "Previously Active Listeners"
}, {
  "artistName" : "Diamond Platnumz",
  "segment" : "Previously Active Listeners"
}, {
  "artistName" : "Calvin Harris",
  "segment" : "Previously Active Listeners"
}, {
  "artistName" : "Gunna",
  "segment" : "Previously Active Listeners"
}, {
  "artistName" : "Shaarib Toshi",
  "segment" : "Previously Active Listeners"
}, {
  "artistName" : "BKTHERULA",
  "segment" : "Previously Active Listeners"
}, {
  "artistName" : "Boyz II Men",
  "segment" : "Previously Active Listeners"
}, {
  "artistName" : "Hasan Raheem",
  "segment" : "Previously Active Listeners"
}, {
  "artistName" : "Lil Kayla",
  "segment" : "Light listeners"
}, {
  "artistName" : "Rahat Fateh Ali Khan",
  "segment" : "Previously Active Listeners"
}, {
  "artistName" : "The PropheC",
  "segment" : "Previously Active Listeners"
}, {
  "artistName" : "Yhapojj",
  "segment" : "Previously Active Listeners"
}, {
  "artistName" : "C2d",
  "segment" : "Previously Active Listeners"
}, {
  "artistName" : "André 3000",
  "segment" : "Previously Active Listeners"
}, {
  "artistName" : "Salim Merchant",
  "segment" : "Previously Active Listeners"
}, {
  "artistName" : "teengore",
  "segment" : "Previously Active Listeners"
}, {
  "artistName" : "Dom Corleo",
  "segment" : "Light listeners"
}, {
  "artistName" : "August Alsina",
  "segment" : "Previously Active Listeners"
}, {
  "artistName" : "100BandXan",
  "segment" : "Light listeners"
}, {
  "artistName" : "Zuko",
  "segment" : "Previously Active Listeners"
}, {
  "artistName" : "Jace!",
  "segment" : "Previously Active Listeners"
}, {
  "artistName" : "Travis Barker",
  "segment" : "Moderate listeners"
}, {
  "artistName" : "GoGetta.Kb",
  "segment" : "Previously Active Listeners"
}, {
  "artistName" : "Conan Gray",
  "segment" : "Previously Active Listeners"
}, {
  "artistName" : "Quando Rondo",
  "segment" : "Moderate listeners"
}, {
  "artistName" : "Marlo",
  "segment" : "Previously Active Listeners"
}, {
  "artistName" : "Keharo",
  "segment" : "Super Listeners"
}, {
  "artistName" : "Drake",
  "segment" : "Light listeners"
}, {
  "artistName" : "Snoop Dogg",
  "segment" : "Previously Active Listeners"
}, {
  "artistName" : "adv",
  "segment" : "Previously Active Listeners"
}, {
  "artistName" : "Usha Mangeshkar",
  "segment" : "Previously Active Listeners"
}, {
  "artistName" : "marvy ayy",
  "segment" : "Light listeners"
}, {
  "artistName" : "Tory Lanez",
  "segment" : "Light listeners"
}, {
  "artistName" : "Iknowwebe",
  "segment" : "Previously Active Listeners"
}, {
  "artistName" : "juno",
  "segment" : "Previously Active Listeners"
}, {
  "artistName" : "Sexyy Red",
  "segment" : "Previously Active Listeners"
}, {
  "artistName" : "Pz'",
  "segment" : "Super Listeners"
}, {
  "artistName" : "Utada",
  "segment" : "Previously Active Listeners"
}, {
  "artistName" : "R. D. Burman",
  "segment" : "Previously Active Listeners"
}, {
  "artistName" : "i love you",
  "segment" : "Previously Active Listeners"
}, {
  "artistName" : "1300SAINT",
  "segment" : "Previously Active Listeners"
}, {
  "artistName" : "Joony",
  "segment" : "Light listeners"
}, {
  "artistName" : "Her's",
  "segment" : "Light listeners"
}, {
  "artistName" : "MF DOOM",
  "segment" : "Previously Active Listeners"
}, {
  "artistName" : "Shaio",
  "segment" : "Super Listeners"
}, {
  "artistName" : "Slxyy",
  "segment" : "Previously Active Listeners"
}, {
  "artistName" : "Meet Bros Anjjan",
  "segment" : "Previously Active Listeners"
}, {
  "artistName" : "Dc2trill",
  "segment" : "Previously Active Listeners"
}, {
  "artistName" : "Three 6 Mafia",
  "segment" : "Previously Active Listeners"
}, {
  "artistName" : "Bighead",
  "segment" : "Light listeners"
}, {
  "artistName" : "Chitra Singh",
  "segment" : "Previously Active Listeners"
}, {
  "artistName" : "Laiken",
  "segment" : "Previously Active Listeners"
}, {
  "artistName" : "Desire",
  "segment" : "Previously Active Listeners"
}, {
  "artistName" : "AT",
  "segment" : "Previously Active Listeners"
}, {
  "artistName" : "Fuzion",
  "segment" : "Previously Active Listeners"
}, {
  "artistName" : "Jessi Levinson",
  "segment" : "Previously Active Listeners"
}, {
  "artistName" : "Panjabi MC",
  "segment" : "Previously Active Listeners"
}, {
  "artistName" : "Young Thug",
  "segment" : "Previously Active Listeners"
}, {
  "artistName" : "Amar Sandhu",
  "segment" : "Previously Active Listeners"
}, {
  "artistName" : "Teejay3k",
  "segment" : "Previously Active Listeners"
}, {
  "artistName" : "Shubh",
  "segment" : "Previously Active Listeners"
}, {
  "artistName" : "Riar Saab",
  "segment" : "Previously Active Listeners"
}, {
  "artistName" : "Gminxr",
  "segment" : "Previously Active Listeners"
}, {
  "artistName" : "Petr Kovar",
  "segment" : "Previously Active Listeners"
}, {
  "artistName" : "yuck",
  "segment" : "Previously Active Listeners"
}, {
  "artistName" : "DJ Scream",
  "segment" : "Previously Active Listeners"
}, {
  "artistName" : "Hardrock",
  "segment" : "Previously Active Listeners"
}, {
  "artistName" : "Pradabagshawty",
  "segment" : "Moderate listeners"
}, {
  "artistName" : "Zukenee",
  "segment" : "Previously Active Listeners"
}, {
  "artistName" : "Manni Sandhu",
  "segment" : "Light listeners"
}, {
  "artistName" : "Owen Harri$",
  "segment" : "Light listeners"
}, {
  "artistName" : "Yungstar",
  "segment" : "Previously Active Listeners"
}, {
  "artistName" : "Gurinder Gill",
  "segment" : "Light listeners"
}, {
  "artistName" : "LUCKI",
  "segment" : "Previously Active Listeners"
}, {
  "artistName" : "Warhol.SS",
  "segment" : "Previously Active Listeners"
}, {
  "artistName" : "Homixide Gang",
  "segment" : "Previously Active Listeners"
}, {
  "artistName" : "Lontalius",
  "segment" : "Previously Active Listeners"
}, {
  "artistName" : "Prada Archive",
  "segment" : "Moderate listeners"
}, {
  "artistName" : "Gucci Mane",
  "segment" : "Previously Active Listeners"
}, {
  "artistName" : "SinceWhen",
  "segment" : "Light listeners"
}, {
  "artistName" : "Summrs",
  "segment" : "Light listeners"
}, {
  "artistName" : "OsamaSon",
  "segment" : "Super Listeners"
}, {
  "artistName" : "dyingoutlay",
  "segment" : "Previously Active Listeners"
}, {
  "artistName" : "lifelessgarments",
  "segment" : "Super Listeners"
}, {
  "artistName" : "Provoker",
  "segment" : "Previously Active Listeners"
}, {
  "artistName" : "BROCKHAMPTON",
  "segment" : "Super Listeners"
}, {
  "artistName" : "WiFiGawd",
  "segment" : "Previously Active Listeners"
}, {
  "artistName" : "GoVanni",
  "segment" : "Previously Active Listeners"
}, {
  "artistName" : "s2kblitz!",
  "segment" : "Moderate listeners"
}, {
  "artistName" : "TopOppGen",
  "segment" : "Previously Active Listeners"
}, {
  "artistName" : "Thouxanbanfauni",
  "segment" : "Previously Active Listeners"
}, {
  "artistName" : "DESTIN CONRAD",
  "segment" : "Previously Active Listeners"
}, {
  "artistName" : "Omarion",
  "segment" : "Previously Active Listeners"
}, {
  "artistName" : "Rai Panesar",
  "segment" : "Previously Active Listeners"
}, {
  "artistName" : "untiljapan",
  "segment" : "Previously Active Listeners"
}, {
  "artistName" : "Snk",
  "segment" : "Previously Active Listeners"
}, {
  "artistName" : "Rx",
  "segment" : "Previously Active Listeners"
}, {
  "artistName" : "nappy 01'",
  "segment" : "Light listeners"
}, {
  "artistName" : "Southsidesilhouette",
  "segment" : "Super Listeners"
}, {
  "artistName" : "Linear Phase",
  "segment" : "Previously Active Listeners"
}, {
  "artistName" : "SeptembersRich",
  "segment" : "Light listeners"
}, {
  "artistName" : "BashfortheWorld",
  "segment" : "Previously Active Listeners"
}, {
  "artistName" : "Slimesito",
  "segment" : "Light listeners"
}, {
  "artistName" : "Yo La Tengo",
  "segment" : "Previously Active Listeners"
}, {
  "artistName" : "AP Dhillon",
  "segment" : "Light listeners"
}, {
  "artistName" : "relmigo",
  "segment" : "Moderate listeners"
}, {
  "artistName" : "Grouper",
  "segment" : "Light listeners"
}, {
  "artistName" : "sawyer",
  "segment" : "Light listeners"
}, {
  "artistName" : "Chicken P",
  "segment" : "Moderate listeners"
}, {
  "artistName" : "elijxhwtf",
  "segment" : "Previously Active Listeners"
}, {
  "artistName" : "UnoTheActivist",
  "segment" : "Previously Active Listeners"
}, {
  "artistName" : "Fenix Flexin",
  "segment" : "Previously Active Listeners"
}, {
  "artistName" : "Denizlpsevv",
  "segment" : "Moderate listeners"
}, {
  "artistName" : "Crumb",
  "segment" : "Previously Active Listeners"
}, {
  "artistName" : "Jaani",
  "segment" : "Previously Active Listeners"
}, {
  "artistName" : "Asha Bhosle",
  "segment" : "Previously Active Listeners"
}, {
  "artistName" : "jetsonmade",
  "segment" : "Previously Active Listeners"
}, {
  "artistName" : "Yunggoth✰",
  "segment" : "Previously Active Listeners"
}, {
  "artistName" : "Petr",
  "segment" : "Previously Active Listeners"
}, {
  "artistName" : "42 Dugg",
  "segment" : "Previously Active Listeners"
}, {
  "artistName" : "Atif Aslam",
  "segment" : "Light listeners"
}, {
  "artistName" : "Karam Brar",
  "segment" : "Previously Active Listeners"
}, {
  "artistName" : "Amaal Mallik",
  "segment" : "Light listeners"
}, {
  "artistName" : "blindheart",
  "segment" : "Previously Active Listeners"
}, {
  "artistName" : "The Goo Goo Dolls",
  "segment" : "Previously Active Listeners"
}, {
  "artistName" : "Don Spiritz",
  "segment" : "Light listeners"
}, {
  "artistName" : "Lil Shine",
  "segment" : "Previously Active Listeners"
}, {
  "artistName" : "Black Smurf",
  "segment" : "Previously Active Listeners"
}, {
  "artistName" : "Slxyy",
  "segment" : "Previously Active Listeners"
}, {
  "artistName" : "Foreigner",
  "segment" : "Light listeners"
}, {
  "artistName" : "MAF Teeski",
  "segment" : "Previously Active Listeners"
}, {
  "artistName" : "Diljit Dosanjh",
  "segment" : "Previously Active Listeners"
}, {
  "artistName" : "Big Scarr",
  "segment" : "Previously Active Listeners"
}, {
  "artistName" : "Yeat",
  "segment" : "Super Listeners"
}, {
  "artistName" : "Peewee Longway",
  "segment" : "Previously Active Listeners"
}, {
  "artistName" : "Shania Twain",
  "segment" : "Light listeners"
}, {
  "artistName" : "$amaad",
  "segment" : "Light listeners"
}, {
  "artistName" : "OHGEESY",
  "segment" : "Previously Active Listeners"
}, {
  "artistName" : "Plaqueboymax",
  "segment" : "Previously Active Listeners"
}, {
  "artistName" : "Shinda Kahlon",
  "segment" : "Previously Active Listeners"
}, {
  "artistName" : "Bandmanfari",
  "segment" : "Light listeners"
}, {
  "artistName" : "rainy bear",
  "segment" : "Previously Active Listeners"
}, {
  "artistName" : "LXST CXNTURY",
  "segment" : "Previously Active Listeners"
}, {
  "artistName" : "Sean Paul",
  "segment" : "Previously Active Listeners"
}, {
  "artistName" : "Saltyngget",
  "segment" : "Previously Active Listeners"
}, {
  "artistName" : "The Weeknd",
  "segment" : "Light listeners"
}, {
  "artistName" : "Sidhu Moose Wala",
  "segment" : "Previously Active Listeners"
}, {
  "artistName" : "Phoebe Bridgers",
  "segment" : "Previously Active Listeners"
}, {
  "artistName" : "Breskii",
  "segment" : "Previously Active Listeners"
}, {
  "artistName" : "Bryson Tiller",
  "segment" : "Previously Active Listeners"
}, {
  "artistName" : "DeeBaby",
  "segment" : "Light listeners"
}, {
  "artistName" : "Kendrick Lamar",
  "segment" : "Previously Active Listeners"
}, {
  "artistName" : "rinoswrld",
  "segment" : "Previously Active Listeners"
}, {
  "artistName" : "Hippie Sabotage",
  "segment" : "Previously Active Listeners"
}, {
  "artistName" : "Majid Jordan",
  "segment" : "Previously Active Listeners"
}, {
  "artistName" : "SiimplySwag",
  "segment" : "Previously Active Listeners"
}, {
  "artistName" : "Neeti Mohan",
  "segment" : "Previously Active Listeners"
}, {
  "artistName" : "t5xy",
  "segment" : "Previously Active Listeners"
}, {
  "artistName" : "Nick Mira",
  "segment" : "Light listeners"
}, {
  "artistName" : "Prabh Singh",
  "segment" : "Light listeners"
}, {
  "artistName" : "yvngn0rfside",
  "segment" : "Previously Active Listeners"
}, {
  "artistName" : "U2",
  "segment" : "Light listeners"
}, {
  "artistName" : "Juicy J",
  "segment" : "Previously Active Listeners"
}, {
  "artistName" : "Lil Thrift",
  "segment" : "Previously Active Listeners"
}, {
  "artistName" : "ziPbby",
  "segment" : "Previously Active Listeners"
}, {
  "artistName" : "ian",
  "segment" : "Light listeners"
} ]
